datura/.DS_Store
datura/__init__.py
datura/draw.py
datura-1.0.5.dist-info/WHEEL
datura-1.0.5.dist-info/METADATA
datura-1.0.5.dist-info/RECORD
