Metadata-Version: 2.1
Name: datura
Version: 1.0.5
Summary: A small pure Python data visualization package
Author-email: Peter Weir <peter.weir@gmail.com>
Classifier: Programming Language :: Python :: 3
Classifier: License :: OSI Approved :: MIT License
Classifier: Operating System :: OS Independent
Project-URL: Documentation, https://datura.readthedocs.io/en/latest/
Project-URL: Source, https://github.com/ptweir/datura
